{
  "tests": [
    {
      "name": "T1",
      "setup": "",
      "run": "g++ -std=c++11 main.cpp && ./a.out",
      "input": "10",
      "output": "[\\w,\\W]*990\\.00[\\w,\\W]*\\n[\\w,\\W]*198\\.00[\\w,\\W]*\\n[\\w,\\W]*792\\.00[\\w,\\W]*",
      "comparison": "regex",
      "timeout": 10,
      "points": 1
    },
    {
      "name": "T2",
      "setup": "",
      "run": "g++ -std=c++11 main.cpp && ./a.out",
      "input": "150",
      "output": "[\\w,\\W]*14850\\.00[\\w,\\W]*\\n[\\w,\\W]*7425\\.00[\\w,\\W]*\\n[\\w,\\W]*7425\\.00[\\w,\\W]*",
      "comparison": "regex",
      "timeout": 10,
      "points": 1
    },
    {
      "name": "T3",
      "setup": "",
      "run": "g++ -std=c++11 main.cpp && ./a.out",
      "input": "75",
      "output": "[\\w,\\W]*7425\\.00[\\w,\\W]*\\n[\\w,\\W]*2970\\.00[\\w,\\W]*\\n[\\w,\\W]*4455\\.00[\\w,\\W]*",
      "comparison": "regex",
      "timeout": 10,
      "points": 1
    }
  ]
}